{
    "filerobot-api-test-button": {
        "title": "Testverbindung von/zu Filerobot",
        "success": "Verbindung wurde erfolgreich getestet.",
        "errors": {
            "failToVerifyFilerobotToken": "Die Verbindung konnte nicht hergestellt werden. Bitte überprüfen Sie Filerobot Token und Security Template Identifier.",
            "failToVerifyAdminAuthToken": "Verbindung konnte nicht hergestellt werden. Bitte überprüfen Sie Admin-Zugriffsschlüssel-ID und geheimen Admin-Zugriffsschlüssel."
        },
        "button": "Verbindung wird getestet"
    },
    "frWidgetLocale": {
        "locale": "DE",
        "button": {
            "export": "Exportieren",
            "processing": "Wird bearbeitet"
        }
    },
    "frErrors": {
        "unauthorized": "Filerobot is unauthorized.",
        "failedToGetKey": "Filerobot has failed to get key.",
        "tokenOrSEC": "Filerobot token or Security template identifier is empty. Please check again your plugin configuration.",
        "notActive": "Filerobot is not active. Please check again your plugin configuration.",
        "cleanMediaFail": "Clean up media had failed.",
        "adminAuthToken": "Can't get admin auth token. Please check again your plugin configuration."
    }
}
